resgen/__init__.py
resgen/aws.py
resgen/cli.py
resgen/exceptions.py
resgen/license.py
resgen/manage.py
resgen/utils.py
resgen/list/__init__.py
resgen/list/commands.py
resgen/sync/__init__.py
resgen/sync/commands.py
resgen/sync/folder.py
resgen_python-0.12.2.dist-info/METADATA
resgen_python-0.12.2.dist-info/WHEEL
resgen_python-0.12.2.dist-info/entry_points.txt
resgen_python-0.12.2.dist-info/top_level.txt
resgen_python-0.12.2.dist-info/RECORD
