Metadata-Version: 2.4
Name: resgen-python
Version: 0.12.2
Summary: Python bindings for the resgen genomic data service
Home-page: https://github.com/reservoirgenomics/resgen-python
Author: Peter Kerpedjiev
Author-email: pkerpedjiev@gmail.com
Keywords: resgen
Classifier: Development Status :: 4 - Beta
Classifier: Intended Audience :: Developers
Classifier: Intended Audience :: Science/Research
Classifier: Topic :: Multimedia :: Graphics
Classifier: Programming Language :: Python :: 3
Classifier: Programming Language :: Python :: 3.3
Classifier: Programming Language :: Python :: 3.4
Classifier: Programming Language :: Python :: 3.5
Classifier: Programming Language :: Python :: 3.6
Classifier: Programming Language :: Python :: 3.7
Requires-Dist: certifi>=2020.06.20
Requires-Dist: boto3
Requires-Dist: click>=7.1.1
Requires-Dist: requests>=2.24.0
Requires-Dist: slugid==2.0.0
Requires-Dist: higlass-python>=1.3.3
Requires-Dist: python-dotenv==0.12.0
Dynamic: author
Dynamic: author-email
Dynamic: classifier
Dynamic: description-content-type
Dynamic: home-page
Dynamic: keywords
Dynamic: requires-dist
Dynamic: summary
